odoo/addons/mail_inline_css/README.rst
odoo/addons/mail_inline_css/__init__.py
odoo/addons/mail_inline_css/__manifest__.py
odoo/addons/mail_inline_css/demo/demo_mail_template.xml
odoo/addons/mail_inline_css/i18n/de.po
odoo/addons/mail_inline_css/i18n/es.po
odoo/addons/mail_inline_css/i18n/es_MX.po
odoo/addons/mail_inline_css/i18n/fr.po
odoo/addons/mail_inline_css/i18n/hr.po
odoo/addons/mail_inline_css/i18n/it.po
odoo/addons/mail_inline_css/i18n/mail_inline_css.pot
odoo/addons/mail_inline_css/i18n/nl_NL.po
odoo/addons/mail_inline_css/i18n/zh_CN.po
odoo/addons/mail_inline_css/models/__init__.py
odoo/addons/mail_inline_css/models/mail_template.py
odoo/addons/mail_inline_css/readme/CONTRIBUTORS.md
odoo/addons/mail_inline_css/readme/CREDITS.md
odoo/addons/mail_inline_css/readme/DESCRIPTION.md
odoo/addons/mail_inline_css/static/description/icon.png
odoo/addons/mail_inline_css/static/description/index.html
odoo/addons/mail_inline_css/tests/__init__.py
odoo/addons/mail_inline_css/tests/test_mail_inline_styles.py
odoo_addon_mail_inline_css-18.0.1.0.0.5.dist-info/METADATA
odoo_addon_mail_inline_css-18.0.1.0.0.5.dist-info/WHEEL
odoo_addon_mail_inline_css-18.0.1.0.0.5.dist-info/top_level.txt
odoo_addon_mail_inline_css-18.0.1.0.0.5.dist-info/RECORD
