Metadata-Version: 2.1
Name: odoo-addon-mail_inline_css
Version: 18.0.1.0.0.5
Requires-Python: >=3.10
Requires-Dist: odoo==18.0.*
Requires-Dist: premailer
Summary: Convert style tags in inline style in your mails
Home-page: https://github.com/OCA/mail
License: AGPL-3
Author: Akretion, camptocamp, Odoo Community Association (OCA)
Author-email: support@odoo-community.org
Classifier: Programming Language :: Python
Classifier: Framework :: Odoo
Classifier: Framework :: Odoo :: 18.0
Classifier: License :: OSI Approved :: GNU Affero General Public License v3
